gitcontrib.py
gitcontrib-0.1.0.dist-info/DESCRIPTION.rst
gitcontrib-0.1.0.dist-info/METADATA
gitcontrib-0.1.0.dist-info/RECORD
gitcontrib-0.1.0.dist-info/WHEEL
gitcontrib-0.1.0.dist-info/entry_points.txt
gitcontrib-0.1.0.dist-info/metadata.json
gitcontrib-0.1.0.dist-info/top_level.txt
