Metadata-Version: 2.0
Name: gitcontrib
Version: 0.1.0
Summary: Compare the activity of different git contributors.
Home-page: https://github.com/DeltaHeavy/git-contrib
Author: Max Zinkus
Author-email: mzinkus@calpoly.edu
License: MIT
Platform: UNKNOWN
Classifier: Development Status :: 4 - Beta
Classifier: Intended Audience :: Developers
Classifier: License :: OSI Approved :: MIT License
Provides-Extra: testing
Requires-Dist: pytest; extra == 'testing'
Requires-Dist: pytest-cov; extra == 'testing'
Requires-Dist: pytest-pep257; extra == 'testing'
Requires-Dist: pytest-pep8; extra == 'testing'
